MANIFEST.in
README.txt
setup.cfg
setup.py
docs/HISTORY.txt
docs/INSTALL.txt
docs/LICENSE.GPL
docs/LICENSE.txt
redomino/__init__.py
redomino/__init__.pyc
redomino.protectdelete.egg-info/PKG-INFO
redomino.protectdelete.egg-info/SOURCES.txt
redomino.protectdelete.egg-info/dependency_links.txt
redomino.protectdelete.egg-info/entry_points.txt
redomino.protectdelete.egg-info/namespace_packages.txt
redomino.protectdelete.egg-info/not-zip-safe
redomino.protectdelete.egg-info/requires.txt
redomino.protectdelete.egg-info/top_level.txt
redomino/protectdelete/__init__.py
redomino/protectdelete/config.py
redomino/protectdelete/configure.zcml
redomino/protectdelete/handlers.py
redomino/protectdelete/i18n.sh
redomino/protectdelete/interfaces.py
redomino/protectdelete/tests.py
redomino/protectdelete/locales/redomino.protectdelete.pot
redomino/protectdelete/locales/en/LC_MESSAGES/README.txt
redomino/protectdelete/locales/en/LC_MESSAGES/redomino.protectdelete.po
redomino/protectdelete/locales/it/LC_MESSAGES/README.txt
redomino/protectdelete/locales/it/LC_MESSAGES/redomino.protectdelete.po
redomino/protectdelete/profiles/default/metadata.xml