Metadata-Version: 1.0
Name: redomino.protectdelete
Version: 0.3
Summary: Avoid objects from delete
Home-page: https://github.com/redomino/redomino.protectdelete
Author: Davide Moro
Author-email: davide.moro@redomino.com
License: GPL
Platform: UNKNOWN
Classifier: Framework :: Plone
Classifier: Programming Language :: Python
